ament_mypy/__init__.py
ament_mypy/main.py
ament_mypy/pytest_marker.py
ament_mypy/configuration/ament_mypy.ini
ament_mypy-0.14.2.data/data/share/ament_index/resource_index/packages/ament_mypy
ament_mypy-0.14.2.data/data/share/ament_mypy/package.xml
ament_mypy-0.14.2.dist-info/METADATA
ament_mypy-0.14.2.dist-info/WHEEL
ament_mypy-0.14.2.dist-info/entry_points.txt
ament_mypy-0.14.2.dist-info/top_level.txt
ament_mypy-0.14.2.dist-info/RECORD
